{
  "updatedAt": "2026-07-14T11:08:20.391Z",
  "timezone": "America/Toronto",
  "stations": {
    "chyz": {
      "id": "chyz",
      "name": "CHYZ 94,3",
      "current": null,
      "next": {
        "title": "Mardi Champ Gauche",
        "source": "schedule",
        "start": "08:00",
        "end": "10:00",
        "url": "https://chyz.ca/emission/mardi-champ-gauche-playlist-du-matin/"
      },
      "track": "",
      "showTitle": "",
      "host": "",
      "source": "schedule",
      "sources": [
        "schedule"
      ],
      "clientPoll": null,
      "checkedAt": "2026-07-14T11:07:57.907Z"
    },
    "cism": {
      "id": "cism",
      "name": "CISM 89,3",
      "current": {
        "title": "À l'horizon",
        "source": "api-live",
        "start": "03:00",
        "url": "https://stream03.ustream.ca/cism128.mp3",
        "slug": "a-lhorizon"
      },
      "next": {
        "title": "Le Séismix",
        "source": "api-live",
        "start": "05:00",
        "url": "https://podcast.cism893.ca/podcast/download_mp3/364290.mp3",
        "slug": "le-seismix"
      },
      "track": "",
      "showTitle": "À l'horizon",
      "host": "",
      "source": "api-live",
      "sources": [
        "api-live"
      ],
      "clientPoll": {
        "type": "cism-v1",
        "url": "https://admin.cism893.ca/api/v1/live"
      },
      "checkedAt": "2026-07-14T11:07:59.768Z"
    },
    "ckut": {
      "id": "ckut",
      "name": "CKUT 90,3",
      "current": {
        "title": "Tuesday Morning After Pt1",
        "source": "api-live",
        "start": "07:00",
        "end": "08:00"
      },
      "next": {
        "title": "Tuesday Morning After Pt2",
        "source": "api-live",
        "start": "08:00",
        "end": "09:00"
      },
      "track": "",
      "showTitle": "Tuesday Morning After Pt1",
      "host": "",
      "source": "api-live",
      "sources": [
        "api-live",
        "stream"
      ],
      "clientPoll": null,
      "checkedAt": "2026-07-14T11:08:02.880Z"
    },
    "cjlo": {
      "id": "cjlo",
      "name": "CJLO 1690AM",
      "current": {
        "title": "Hip's Time to Wake Hop",
        "source": "schedule",
        "start": "06:00",
        "end": "09:00",
        "url": "http://www.cjlo.com/shows/hips-time-to-wake-hop"
      },
      "next": {
        "title": "At The Movies",
        "source": "schedule",
        "start": "09:00",
        "end": "10:00",
        "url": "http://www.cjlo.com/shows/at-the-movies"
      },
      "track": "",
      "showTitle": "Hip's Time to Wake Hop",
      "host": "",
      "source": "schedule",
      "sources": [
        "schedule"
      ],
      "clientPoll": null,
      "checkedAt": "2026-07-14T11:08:16.636Z"
    },
    "cfak": {
      "id": "cfak",
      "name": "CFAK 88,3",
      "current": {
        "title": "Folkswagen",
        "source": "schedule",
        "start": "07:00",
        "end": "08:00"
      },
      "next": {
        "title": "Palmarès CFAK",
        "source": "schedule",
        "start": "08:00",
        "end": "18:30"
      },
      "track": "",
      "showTitle": "Folkswagen",
      "host": "",
      "source": "schedule",
      "sources": [
        "schedule"
      ],
      "clientPoll": null,
      "checkedAt": "2026-07-14T11:08:17.614Z"
    },
    "choq": {
      "id": "choq",
      "name": "CHOQ.ca",
      "current": {
        "title": "Les avions",
        "source": "api-live",
        "host": "Bonne nuit, chérie"
      },
      "next": null,
      "track": "Bonne nuit, chérie - Les avions",
      "showTitle": "Les avions",
      "host": "Bonne nuit, chérie",
      "source": "api-live",
      "sources": [
        "api-live",
        "stream"
      ],
      "clientPoll": null,
      "checkedAt": "2026-07-14T11:08:20.040Z"
    }
  }
}
